Metadata-Version: 2.1
Name: streamlit-auth-mfa
Version: 6.1.3
Summary: A robust library for authentication with Streamlit, featuring 2FA, permissions, and session management.
Home-page: https://github.com/joaopalmeidao/streamlit_auth
Author: João Pedro Almeida Oliveira
Author-email: jp080496@gmail.com
Classifier: Programming Language :: Python :: 3
Classifier: License :: OSI Approved :: MIT License
Classifier: Operating System :: OS Independent
Requires-Python: >=3.9
License-File: LICENCE
Requires-Dist: streamlit==1.41.1
Requires-Dist: sqlalchemy==1.4.45
Requires-Dist: bcrypt==4.0.1
Requires-Dist: pandas==1.5.1
Requires-Dist: numpy==1.26.4
Requires-Dist: pyotp==2.9.0
Requires-Dist: qrcode==8.0
Requires-Dist: extra-streamlit-components==0.1.60
Requires-Dist: python-dotenv==1.0.1
Provides-Extra: dev
Requires-Dist: pytest; extra == "dev"
Requires-Dist: pytest-mock; extra == "dev"
Requires-Dist: twine; extra == "dev"
